main.py
video2pdf_cli-0.1.0.dist-info/METADATA
video2pdf_cli-0.1.0.dist-info/WHEEL
video2pdf_cli-0.1.0.dist-info/entry_points.txt
video2pdf_cli-0.1.0.dist-info/RECORD
